sherlock_lit/__init__.py
sherlock_lit/cli.py
sherlock_lit/core.py
sherlock_lit-0.1.4.dist-info/LICENSE
sherlock_lit-0.1.4.dist-info/METADATA
sherlock_lit-0.1.4.dist-info/WHEEL
sherlock_lit-0.1.4.dist-info/entry_points.txt
sherlock_lit-0.1.4.dist-info/top_level.txt
sherlock_lit-0.1.4.dist-info/RECORD
