Metadata-Version: 2.1
Name: sherlock-lit
Version: 0.1.4
Summary: Sherlock-lit helps you get everything an Abstract hides with a fast technical description card (Research questions, contribution, possible future works) of an NLP paper before reading it.
Home-page: https://github.com/anvix9/sherlock
Author: Anvi Alex E.
Author-email: epononanvi@gmail.com
Classifier: Programming Language :: Python :: 3
Classifier: License :: OSI Approved :: MIT License
Classifier: Operating System :: OS Independent
Requires-Python: >=3.11
License-File: LICENSE
Requires-Dist: requests>=2.25.1
Requires-Dist: docling
Requires-Dist: arxiv
Requires-Dist: ollama
